{
  "project_info": {
    "project_number": "176995673057",
    "project_id": "justcr-305b5",
    "storage_bucket": "justcr-305b5.firebasestorage.app"
  },
  "client": [
    {
      "client_info": {
        "mobilesdk_app_id": "1:176995673057:android:ae7de7787704ba238968a0",
        "android_client_info": {
          "package_name": "com.readme.justcr"
        }
      },
      "oauth_client": [],
      "api_key": [
        {
          "current_key": "AIzaSyCb8gSE4p8hjhoyX_OX8xoTm9gzcOZh7wU"
        }
      ],
      "services": {
        "appinvite_service": {
          "other_platform_oauth_client": []
        }
      }
    }
  ],
  "configuration_version": "1"
}